CHANGELOG.md
LICENSE.md
README.md
example.png
setup.py
orderfix/__init__.py
orderfix/orderfix.c
orderfix/orderfix.pyx
orderfix.egg-info/PKG-INFO
orderfix.egg-info/SOURCES.txt
orderfix.egg-info/dependency_links.txt
orderfix.egg-info/not-zip-safe
orderfix.egg-info/requires.txt
orderfix.egg-info/top_level.txt
test/orderfix_test.py